choreopath/__init__.py
choreopath/cli.py
choreopath/colors.py
choreopath/svg_generator.py
choreopath/tracking_data.py
choreopath/video.py
choreopath/video_overlay_renderer.py
choreopath-1.2.0.dist-info/entry_points.txt
choreopath-1.2.0.dist-info/licenses/LICENSE.md
choreopath-1.2.0.dist-info/WHEEL
choreopath-1.2.0.dist-info/METADATA
choreopath-1.2.0.dist-info/RECORD
