Metadata-Version: 2.4
Name: choreopath
Version: 1.2.0
Summary: Transform human movement into generative art. Track body poses from video and create SVG visualizations of motion trajectories
Requires-Python: >=3.12,<3.13
License-File: LICENSE.md
Requires-Dist: click>=8.3.0
Requires-Dist: mediapipe>=0.10.21
Requires-Dist: opencv-python>=4.11.0.86
Requires-Dist: pandas>=2.3.3
Requires-Dist: matplotlib>=3.7.0
